django_postalcodes-0.4.0.dist-info/DESCRIPTION.rst
django_postalcodes-0.4.0.dist-info/METADATA
django_postalcodes-0.4.0.dist-info/metadata.json
django_postalcodes-0.4.0.dist-info/RECORD
django_postalcodes-0.4.0.dist-info/top_level.txt
django_postalcodes-0.4.0.dist-info/WHEEL
postalcodes/__init__.py
postalcodes/admin.py
postalcodes/models.py
postalcodes/migrations/0001_initial.py
postalcodes/migrations/__init__.py
postalcodes/south_migrations/0001_initial.py
postalcodes/south_migrations/0002_auto__del_field_postalcode_latitude__del_field_postalcode_longitude__a.py
postalcodes/south_migrations/__init__.py
