Metadata-Version: 2.0
Name: django-postalcodes
Version: 0.4.0
Summary: Postal code management.
Home-page: https://github.com/bennylope/django-postalcodes/
Author: Ben Lopatin
Author-email: ben.lopatin@wellfireinteractive.com
License: BSD License
Platform: OS Independent
Classifier: Development Status :: 3 - Alpha
Classifier: Environment :: Web Environment
Classifier: Intended Audience :: Developers
Classifier: License :: OSI Approved :: BSD License
Classifier: Operating System :: OS Independent
Classifier: Programming Language :: Python
Classifier: Framework :: Django
Requires-Dist: Django (>=1.3)
